RTRAConnect/RTRAConnect.py
RTRAConnect/__init__.py
RTRAConnnect/RTRAConnect.py
RTRAConnnect/__init__.py
eternity/RTRAConnect.py
eternity/__init__.py
RTRAConnect-0.1.0.dist-info/LICENSE
RTRAConnect-0.1.0.dist-info/METADATA
RTRAConnect-0.1.0.dist-info/WHEEL
RTRAConnect-0.1.0.dist-info/top_level.txt
RTRAConnect-0.1.0.dist-info/RECORD
